LICENSE
README.rst
setup.py
termineter
lib/c1218/__init__.py
lib/c1218/connection.py
lib/c1218/data.py
lib/c1218/errors.py
lib/c1218/utilities.py
lib/c1218/urlhandler/__init__.py
lib/c1218/urlhandler/protocol_unix.py
lib/c1219/__init__.py
lib/c1219/constants.py
lib/c1219/data.py
lib/c1219/errors.py
lib/c1219/access/__init__.py
lib/c1219/access/general.py
lib/c1219/access/local_display.py
lib/c1219/access/log.py
lib/c1219/access/security.py
lib/c1219/access/telephone.py
lib/c1222/__init__.py
lib/c1222/connection.py
lib/c1222/data.py
lib/c1222/errors.py
lib/c1222/utilities.py
lib/termineter/__init__.py
lib/termineter/cmd.py
lib/termineter/core.py
lib/termineter/errors.py
lib/termineter/interface.py
lib/termineter/its.py
lib/termineter/module.py
lib/termineter/options.py
lib/termineter/utilities.py
lib/termineter.egg-info/PKG-INFO
lib/termineter.egg-info/SOURCES.txt
lib/termineter.egg-info/dependency_links.txt
lib/termineter.egg-info/requires.txt
lib/termineter.egg-info/top_level.txt
lib/termineter/data/smeter_passwords.txt
lib/termineter/modules/__init__.py
lib/termineter/modules/brute_force_login.py
lib/termineter/modules/diff_tables.py
lib/termineter/modules/dump_tables.py
lib/termineter/modules/enum_tables.py
lib/termineter/modules/enum_user_ids.py
lib/termineter/modules/get_identification.py
lib/termineter/modules/get_info.py
lib/termineter/modules/get_local_display_info.py
lib/termineter/modules/get_log_info.py
lib/termineter/modules/get_modem_info.py
lib/termineter/modules/get_security_info.py
lib/termineter/modules/read_table.py
lib/termineter/modules/remote_reset.py
lib/termineter/modules/run_procedure.py
lib/termineter/modules/set_meter_id.py
lib/termineter/modules/set_meter_mode.py
lib/termineter/modules/write_table.py