Metadata-Version: 2.1
Name: termineter
Version: 1.0.6
Summary: Termineter is a Python framework which provides a platform for the security testing of smart meters.
Home-page: https://github.com/securestate/termineter
Author: Spencer McIntyre
Author-email: smcintyre@securestate.com
Maintainer: Spencer McIntyre
License: BSD
Classifier: Development Status :: 5 - Production/Stable
Classifier: Environment :: Console
Classifier: License :: OSI Approved :: BSD License
Classifier: Operating System :: OS Independent
Classifier: Programming Language :: Python :: 3.4
Classifier: Programming Language :: Python :: 3.5
Classifier: Programming Language :: Python :: 3.6
Classifier: Programming Language :: Python :: 3.7
Classifier: Programming Language :: Python :: 3.8
Classifier: Programming Language :: Python :: 3.9
Classifier: Programming Language :: Python :: 3.10
Classifier: Programming Language :: Python :: 3.11
Classifier: Programming Language :: Python :: 3.12
Classifier: Topic :: Security
License-File: LICENSE
Requires-Dist: crcelk>=1.3
Requires-Dist: pluginbase>=1.0.0
Requires-Dist: pyasn1>=0.4.5
Requires-Dist: pyserial>=3.4
Requires-Dist: smoke-zephyr>=1.2
Requires-Dist: tabulate>=0.8.3
Requires-Dist: termcolor>=1.1.0
